hello_word/__init__.py
hello_word/client.py
hello_world_cc-0.0.5.dist-info/LICENSE
hello_world_cc-0.0.5.dist-info/METADATA
hello_world_cc-0.0.5.dist-info/WHEEL
hello_world_cc-0.0.5.dist-info/top_level.txt
hello_world_cc-0.0.5.dist-info/RECORD
