Metadata-Version: 2.1
Name: hello-world-cc
Version: 0.0.5
Summary: the Official W3bstream Client for Python
Author: haaai
Author-email: chenchen <chen1233216@hotmail.com>
License: Apache License
License-File: LICENSE
Requires-Dist: requests
Requires-Dist: typeguard
